snamosim/__init__.py
snamosim/behavior_report.py
snamosim/main.py
snamosim/sandbox.py
snamosim/simulator.py
snamosim/behaviors/__init__.py
snamosim/behaviors/baseline_behavior.py
snamosim/behaviors/navigation_only_behavior.py
snamosim/behaviors/plan_report.py
snamosim/behaviors/stilman_2005_behavior.py
snamosim/behaviors/wu_levihn_2014_behavior.py
snamosim/behaviors/algorithms/__init__.py
snamosim/behaviors/algorithms/best_first_search.py
snamosim/behaviors/algorithms/cell_heap_node.py
snamosim/behaviors/algorithms/d_star_lite.py
snamosim/behaviors/algorithms/graph_search.py
snamosim/behaviors/algorithms/multi_goal_a_star.py
snamosim/behaviors/algorithms/new_local_opening_check.py
snamosim/behaviors/plan/__init__.py
snamosim/behaviors/plan/action_result.py
snamosim/behaviors/plan/basic_actions.py
snamosim/behaviors/plan/path.py
snamosim/behaviors/plan/plan.py
snamosim/behaviors/plan/plan_step.py
snamosim/display/__init__.py
snamosim/display/painter.py
snamosim/display/ros_conversion.py
snamosim/display/ros_publisher.py
snamosim/display/ros_publisher_config.py
snamosim/display/tf_replacement.py
snamosim/display/triangulate.py
snamosim/tests/__init__.py
snamosim/tests/sandbox.py
snamosim/tests/integration_tests/__init__.py
snamosim/tests/integration_tests/first_level/__init__.py
snamosim/tests/integration_tests/first_level/big_crossing_test.py
snamosim/tests/integration_tests/first_level/two_rooms_corridor_test.py
snamosim/tests/integration_tests/moghaddam_planning_2016_benchmark/__init__.py
snamosim/tests/integration_tests/moghaddam_planning_2016_benchmark/moghaddam_planning_2016_benchmark_01_test.py
snamosim/tests/integration_tests/s-namo_cases/__init__.py
snamosim/tests/integration_tests/s-namo_cases/after_the_feast_test.py
snamosim/tests/integration_tests/s-namo_cases/basic_test.py
snamosim/tests/integration_tests/s-namo_cases/basic_with_opening_test.py
snamosim/tests/integration_tests/s-namo_cases/citi_second_floor.py
snamosim-0.3.2.dist-info/LICENSE
snamosim-0.3.2.dist-info/METADATA
snamosim-0.3.2.dist-info/WHEEL
snamosim-0.3.2.dist-info/top_level.txt
snamosim-0.3.2.dist-info/RECORD
