Metadata-Version: 2.1
Name: snamosim
Version: 0.3.2
Summary: NAMO and S-NAMO Algorithms and tools for robotics.
Home-page: https://gitlab.inria.fr/brenault/s-namo-sim
Author: Benoit RENAULT
Author-email: xia0ben-contact-pypi@littleroot.net
License: UNKNOWN
Platform: UNKNOWN
Classifier: Programming Language :: Python :: 3
Classifier: License :: OSI Approved :: MIT License
Classifier: Operating System :: OS Independent
Requires-Python: >=2.7
Requires-Dist: numpy
Requires-Dist: shapely
Requires-Dist: matplotlib
Requires-Dist: aabbtree
Requires-Dist: mapbox-earcut
Requires-Dist: bidict
Requires-Dist: svgpath2mpl
Requires-Dist: Pillow
Requires-Dist: scikit-image
Requires-Dist: scipy
